pr_agent/__init__.py
pr_agent/cli.py
pr_agent/drive_client.py
pr_agent/notion_client.py
pr_agent/settings.py
pr_agent/connectors/__init__.py
pr_agent/connectors/base_connector.py
pr_agent/connectors/gdrive_connector.py
pr_agent/connectors/notion_connector.py
pr_agent/core/__init__.py
pr_agent/core/embedder.py
pr_agent/core/json_writer.py
pr_agent/core/metadata_manager.py
pr_agent/core/pinecone_manager.py
pr_agent/core/summarizer.py
pr_agent/core/text_extractor.py
pr_agent/scripts/__init__.py
pr_agent/scripts/create_pinecone_index.py
pr_agent/scripts/discover_sources.py
pr_agent/scripts/process_pending.py
internal_tool-0.2.1.dist-info/METADATA
internal_tool-0.2.1.dist-info/WHEEL
internal_tool-0.2.1.dist-info/entry_points.txt
internal_tool-0.2.1.dist-info/top_level.txt
internal_tool-0.2.1.dist-info/RECORD
