Metadata-Version: 2.4
Name: internal-tool
Version: 0.2.1
Summary: A Python agent for discovering and processing documents from Google Drive and Notion.
Home-page: https://github.com/yashaswini2027/internal-tool
Author: yashaswini
Author-email: goyashu@gmail.com
Classifier: Programming Language :: Python :: 3
Classifier: License :: OSI Approved :: MIT License
Classifier: Operating System :: OS Independent
Requires-Python: >=3.8
Requires-Dist: pydantic
Requires-Dist: python-dotenv
Requires-Dist: google-api-python-client
Requires-Dist: notion-client
Requires-Dist: pandas
Requires-Dist: openpyxl
Requires-Dist: google-api-python-client
Requires-Dist: google-auth
Requires-Dist: python-docx
Requires-Dist: PyPDF2
Requires-Dist: sentence-transformers
Requires-Dist: spacy
Requires-Dist: requests
Requires-Dist: numpy
Requires-Dist: pydantic-settings
Requires-Dist: tiktoken
Requires-Dist: transformers
Requires-Dist: torch
Requires-Dist: pinecone
Requires-Dist: pydantic-ai
Requires-Dist: typer
Requires-Dist: pypandoc
Dynamic: author
Dynamic: author-email
Dynamic: classifier
Dynamic: description-content-type
Dynamic: home-page
Dynamic: requires-dist
Dynamic: requires-python
Dynamic: summary
